[
	{
		"service": "WordPress Designer",
		"icon": "wordpress.svg",
		"description": "I create WordPress themes and build complete websites from scratch.",
		"listTitle": "Plugins I use:",
		"list": [
			"Oxygen Builder (theme builder)",
			"Elementor Pro (theme builder)",
			"Meta Box (dynamic data)"
		]
	},
	{
		"service": "Front-end developer",
		"icon": "front-end.svg",
		"description": "I love coding and making dreams come true for websites, apps, etc.",
		"listTitle": "Languages I use:",
		"list": [
			"HTML / CSS",
			"Javascript",
			"React (soon)"
		]
	},
	{
		"service": "Graphic designer",
		"icon": "graphic-design.svg",
		"description": "I will make the perfect logo and branding for your company. Or use your current branding to create whatever you want or need.",
		"listTitle": "Software I use:",
		"list": [
			"Illustrator",
			"Photoshop",
			"InDesign"
		]
	},
	{
		"service": "And more",
		"icon": "front-end.svg",
		"description": "Just give me a ring or send me an email to find out what I can do for you.",
		"listTitle": "Some more I do:",
		"list": [
			"Prototyping (Adobe XD)",
			"PowerPoint presentation design",
			"Car stickers"
		]
	}
]